hobo.py
hobo-0.0.1.dist-info/DESCRIPTION.rst
hobo-0.0.1.dist-info/METADATA
hobo-0.0.1.dist-info/RECORD
hobo-0.0.1.dist-info/WHEEL
hobo-0.0.1.dist-info/metadata.json
hobo-0.0.1.dist-info/top_level.txt
