Metadata-Version: 2.0
Name: hobo
Version: 0.0.1
Summary: A simple module for reading Onset HOBO data logger data
Home-page: https://github.com/nationalparkservice/hobo-py
Author: David A. Riggs
Author-email: david_a_riggs@nps.gov
License: UNKNOWN
Platform: UNKNOWN
Classifier: Development Status :: 3 - Alpha
Classifier: Intended Audience :: Developers
Classifier: Intended Audience :: Science/Research
Classifier: License :: Public Domain
Classifier: License :: CC0 1.0 Universal (CC0 1.0) Public Domain Dedication
